djfilters/__init__.py
djfilters/apps.py
djfilters/backend.py
djfilters/compat.py
djfilters/filters/__init__.py
djfilters/filters/fields.py
djfilters/filters/filters.py
djfilters/templates/djfilters/vertical/checkbox.html
djfilters/templates/djfilters/vertical/checkbox_multiple.html
djfilters/templates/djfilters/vertical/dict_field.html
djfilters/templates/djfilters/vertical/fieldset.html
djfilters/templates/djfilters/vertical/form.html
djfilters/templates/djfilters/vertical/input.html
djfilters/templates/djfilters/vertical/list_field.html
djfilters/templates/djfilters/vertical/list_fieldset.html
djfilters/templates/djfilters/vertical/radio.html
djfilters/templates/djfilters/vertical/select.html
djfilters/templates/djfilters/vertical/select_multiple.html
djfilters/templates/djfilters/vertical/textarea.html
dj_rest_filters-1.0.4.dist-info/LICENSE
dj_rest_filters-1.0.4.dist-info/METADATA
dj_rest_filters-1.0.4.dist-info/WHEEL
dj_rest_filters-1.0.4.dist-info/top_level.txt
dj_rest_filters-1.0.4.dist-info/RECORD
