Metadata-Version: 2.1
Name: dj-rest-filters
Version: 1.0.4
Summary: Django Rest Filter
Home-page: https://github.com/mhsiddiqui/dj-rest-filters
Author: Muhammad Hassan Siddiqui
Author-email: mhassan.eeng@gmail.com
License: MIT
Keywords: django,filters,filter-backend,dj-rest-filters
Platform: any
Classifier: Development Status :: 5 - Production/Stable
Classifier: Environment :: Web Environment
Classifier: Framework :: Django
Classifier: Framework :: Django :: 1.10
Classifier: Framework :: Django :: 2.2
Classifier: Framework :: Django :: 3.0
Classifier: Framework :: Django :: 3.1
Classifier: Framework :: Django :: 3.2
Classifier: Framework :: Django :: 4.0
Classifier: Framework :: Django :: 4.2
Classifier: Intended Audience :: Developers
Classifier: License :: OSI Approved :: MIT License
Classifier: Natural Language :: English
Classifier: Operating System :: OS Independent
Classifier: Programming Language :: Python
Classifier: Programming Language :: Python :: 3
Classifier: Programming Language :: Python :: 3.6
Classifier: Programming Language :: Python :: 3.7
Classifier: Programming Language :: Python :: 3.8
Classifier: Programming Language :: Python :: 3.9
Classifier: Programming Language :: Python :: 3.10
Classifier: Programming Language :: Python :: 3.11
Classifier: Programming Language :: Python :: Implementation :: CPython
Classifier: Programming Language :: Python :: Implementation :: PyPy
Classifier: Topic :: Utilities
Requires-Python: >=3
License-File: LICENSE
Requires-Dist: Django >1.10
Requires-Dist: djangorestframework >3.3
Requires-Dist: six
Requires-Dist: pytz
